eprofiler.py
eprofiler-0.0.5.dist-info/LICENSE
eprofiler-0.0.5.dist-info/METADATA
eprofiler-0.0.5.dist-info/WHEEL
eprofiler-0.0.5.dist-info/top_level.txt
eprofiler-0.0.5.dist-info/RECORD
