Metadata-Version: 2.1
Name: eprofiler
Version: 0.0.5
Summary: a simple tool to monitor execution times of functions.
Home-page: https://github.com/eyukselen/eprofiler
Author: emre
Author-email: 
License: MIT
Project-URL: Homepage, https://github.com/eyukselen
Project-URL: Documentation, https://eprofiler.readthedocs.io/en/latest/index.html
Project-URL: Source, https://github.com/eyukselen/eprofiler
Platform: UNKNOWN
Classifier: Development Status :: 2 - Pre-Alpha
Classifier: Operating System :: OS Independent
Classifier: License :: OSI Approved :: MIT License
Classifier: Programming Language :: Python
Classifier: Programming Language :: Python :: 3
Classifier: Topic :: Software Development :: Libraries :: Python Modules
License-File: LICENSE
